[
  {"id": 1, "question": "What is the scalar (dot) product of two vectors x and y in R^n?", "answer": "xᵀy = x₁y₁ + x₂y₂ + ... + xₙyₙ", "confidence": 0},
  {"id": 2, "question": "What is the Euclidean norm of a vector x?", "answer": "‖x‖ = √(x₁² + x₂² + ... + xₙ²)", "confidence": 0},
  {"id": 3, "question": "What is the relationship between the dot product and the angle between two vectors?", "answer": "xᵀy = ‖x‖‖y‖cosθ, where θ is the smallest angle between x and y.", "confidence": 0},
  {"id": 4, "question": "When are two vectors orthogonal?", "answer": "When their dot product is zero (xᵀy = 0).", "confidence": 0},
  {"id": 5, "question": "What is the vector projection of y onto x?", "answer": "p = (yᵀx / ‖x‖²) x", "confidence": 0},
  {"id": 6, "question": "What is the scalar projection of y onto x?", "answer": "(yᵀx) / ‖x‖", "confidence": 0},
  {"id": 7, "question": "What is the distance from y to the line spanned by x?", "answer": "d = ‖y − p‖, where p is the projection of y onto x.", "confidence": 0},
  {"id": 8, "question": "What is the orthogonal complement Y⊥ of a subspace Y ⊆ Rⁿ?", "answer": "The set of all vectors in Rⁿ that are orthogonal to every vector in Y.", "confidence": 0},
  {"id": 9, "question": "What properties hold for Y and its orthogonal complement Y⊥?", "answer": "Y ∩ Y⊥ = {0}, (Y⊥)⊥ = Y, dim(Y) + dim(Y⊥) = n, and every x ∈ Rⁿ can be written uniquely as x = x_Y + x_Y⊥.", "confidence": 0},
  {"id": 10, "question": "What does the Fundamental Spaces Theorem state for a matrix A?", "answer": "(a) N(A) = R(Aᵀ)⊥, (b) N(Aᵀ) = R(A)⊥.", "confidence": 0},
  {"id": 11, "question": "How can you find a basis for the orthogonal complement S⊥ of a subspace S spanned by {v₁,…,vₖ}?", "answer": "Form A with columns v₁,…,vₖ, then S⊥ = N(Aᵀ). Reduce Aᵀ to row echelon form to find the basis.", "confidence": 0},
  {"id": 12, "question": "What is the goal of least squares for an overdetermined system Ax = b?", "answer": "To find x minimizing ‖b − Ax‖, i.e., minimizing the residual norm.", "confidence": 0},
  {"id": 13, "question": "What are the normal equations for the least squares solution?", "answer": "AᵀA x̂ = Aᵀb", "confidence": 0},
  {"id": 14, "question": "When does the least squares solution exist and is unique?", "answer": "When A has full column rank (rank n).", "confidence": 0},
  {"id": 15, "question": "What is the projection matrix that projects onto the column space of A?", "answer": "P = A(AᵀA)⁻¹Aᵀ", "confidence": 0},
  {"id": 16, "question": "What is the projection vector p for Ax = b?", "answer": "p = A(AᵀA)⁻¹Aᵀb = Pb, the closest vector to b in the column space of A.", "confidence": 0},
  {"id": 17, "question": "How is least squares used for fitting data to a polynomial y = c₀ + c₁x + ... + cₚxᵖ?", "answer": "Form system Xc = y and solve the normal equations XᵀX ĉ = Xᵀy to minimize ‖y − Xc‖.", "confidence": 0},
  {"id": 18, "question": "What is an inner product?", "answer": "An operation 〈x,y〉 assigning a real number to each pair of vectors satisfying positivity, symmetry, and linearity.", "confidence": 0},
  {"id": 19, "question": "Give examples of inner products.", "answer": "Rⁿ: 〈x,y〉=xᵀy; R^(m×n): sum(aᵢⱼbᵢⱼ); C([a,b]): ∫ₐᵇ f(x)g(x)dx; Pₙ: Σp(xᵢ)q(xᵢ).", "confidence": 0},
  {"id": 20, "question": "What is the norm induced by an inner product?", "answer": "‖v‖ = √〈v,v〉", "confidence": 0},
  {"id": 21, "question": "State the Pythagorean Law for orthogonal vectors.", "answer": "If u ⊥ v, then ‖u + v‖² = ‖u‖² + ‖v‖².", "confidence": 0},
  {"id": 22, "question": "What is the scalar projection of u onto v in an inner product space?", "answer": "〈u,v〉 / ‖v‖", "confidence": 0},
  {"id": 23, "question": "What is the vector projection of u onto v in an inner product space?", "answer": "(〈u,v〉 / ‖v‖²) v", "confidence": 0},
  {"id": 24, "question": "How is the angle between two vectors defined in an inner product space?", "answer": "θ = arccos(〈u,v〉 / (‖u‖‖v‖))", "confidence": 0},
  {"id": 25, "question": "What are the norm axioms for a normed vector space?", "answer": "‖v‖≥0, ‖v‖=0⇔v=0; ‖αv‖=|α|‖v‖; ‖v+w‖≤‖v‖+‖w‖.", "confidence": 0},
  {"id": 26, "question": "What are common norms in Rⁿ?", "answer": "‖x‖₁=Σ|xᵢ|, ‖x‖₂=√Σxᵢ², ‖x‖ₚ=(Σ|xᵢ|ᵖ)¹/ᵖ, ‖x‖∞=max|xᵢ|.", "confidence": 0},
  {"id": 27, "question": "When do vectors form an orthogonal set?", "answer": "When 〈vᵢ,vⱼ〉=0 for all i≠j.", "confidence": 0},
  {"id": 28, "question": "What is an orthonormal set?", "answer": "An orthogonal set of unit vectors.", "confidence": 0},
  {"id": 29, "question": "What property do matrices with orthonormal columns satisfy?", "answer": "UᵀU = I.", "confidence": 0},
  {"id": 30, "question": "In an orthonormal basis {uᵢ}, how are coefficients found for v = Σcᵢuᵢ?", "answer": "Each cᵢ = 〈v,uᵢ〉.", "confidence": 0},
  {"id": 31, "question": "What does Parseval’s formula state?", "answer": "If v = Σcᵢuᵢ with orthonormal {uᵢ}, then ‖v‖² = Σcᵢ².", "confidence": 0},
  {"id": 32, "question": "What is the least squares solution when A has orthonormal columns?", "answer": "x̂ = Aᵀb, and P = AAᵀ.", "confidence": 0},
  {"id": 33, "question": "How do you compute the projection of b onto a subspace S with orthonormal basis {u₁,…,uₖ}?", "answer": "p = Σ〈b,uᵢ〉uᵢ.", "confidence": 0},
  {"id": 34, "question": "What is the Gram–Schmidt process used for?", "answer": "To convert a basis {x₁,…,xₙ} into an orthonormal basis {q₁,…,qₙ}.", "confidence": 0},
  {"id": 35, "question": "What is the formula for q₁ in the Gram–Schmidt process?", "answer": "q₁ = x₁ / ‖x₁‖.", "confidence": 0},
  {"id": 36, "question": "How is q₂ computed in the Gram–Schmidt process?", "answer": "q₂ = (x₂ − 〈x₂,q₁〉q₁) / ‖x₂ − 〈x₂,q₁〉q₁‖.", "confidence": 0},
  {"id": 37, "question": "What are the general steps in Gram–Schmidt?", "answer": "For each xₖ, subtract projections onto all previous qᵢ, then normalize the result.", "confidence": 0},
  {"id": 38, "question": "What is QR factorization?", "answer": "A = QR, where Q has orthonormal columns and R is upper triangular with positive diagonal entries.", "confidence": 0},
  {"id": 39, "question": "How are rᵢⱼ values computed in QR factorization?", "answer": "rᵢⱼ = 〈aⱼ, qᵢ〉 for i ≤ j.", "confidence": 0},
  {"id": 40, "question": "How are qᵢ vectors computed in QR factorization?", "answer": "qᵢ = (aᵢ − Σ₍ₖ<ᵢ₎rₖᵢqₖ)/rᵢᵢ.", "confidence": 0},
  {"id": 41, "question": "How can QR factorization be used to solve least squares problems?", "answer": "If A=QR, solve Rx=Qᵀb using back substitution.", "confidence": 0}
]